{
	"configurations" : 
	[
		{
			"directories" : 
			[
				{
					"build" : ".",
					"jsonFile" : "directory-.-RelWithDebInfo-d0094a50bb2071803777.json",
					"minimumCMakeVersion" : 
					{
						"string" : "3.6.0"
					},
					"projectIndex" : 0,
					"source" : "."
				}
			],
			"name" : "RelWithDebInfo",
			"projects" : 
			[
				{
					"directoryIndexes" : 
					[
						0
					],
					"name" : "Project"
				}
			],
			"targets" : []
		}
	],
	"kind" : "codemodel",
	"paths" : 
	{
		"build" : "E:/ticket_hub/android/app/.cxx/RelWithDebInfo/5er6n6d7/x86_64",
		"source" : "C:/Users/ahmed/Downloads/flutter_windows_3.13.4-stable/flutter/packages/flutter_tools/gradle/src/main/groovy"
	},
	"version" : 
	{
		"major" : 2,
		"minor" : 3
	}
}
